Metadata-Version: 2.1
Name: nlu-tmp
Version: 4.3.0
Summary: John Snow Labs NLU provides state of the art algorithms for NLP&NLU with 5000+ of pretrained models in 200+ languages. It enables swift and simple development and research with its powerful Pythonic and Keras inspired API. It is powerd by John Snow Labs powerful Spark NLP library.
Home-page: http://nlu.johnsnowlabs.com
Author: John Snow Labs
Author-email: christian@johnsnowlabs.com
Keywords: NLP spark development NLU
Classifier: Development Status :: 5 - Production/Stable
Classifier: Intended Audience :: Developers
Classifier: Topic :: Software Development :: Build Tools
Classifier: License :: OSI Approved :: Apache Software License
Classifier: Programming Language :: Python :: 2
Classifier: Programming Language :: Python :: 2.7
Classifier: Programming Language :: Python :: 3
Classifier: Programming Language :: Python :: 3.4
Classifier: Programming Language :: Python :: 3.5
Classifier: Programming Language :: Python :: 3.6
License-File: LICENSE
Requires-Dist: spark-nlp (<4.4.0,>=4.2.8)
Requires-Dist: numpy
Requires-Dist: pyarrow (>=0.16.0)
Requires-Dist: pandas (>=1.3.5)
Requires-Dist: dataclasses
